solid2_legacy/__init__.py
solid2_legacy/bill_of_materials.py
solid2_legacy/examples/legacy/__init__.py
solid2_legacy/examples/legacy/basic_builtins.py
solid2_legacy/examples/legacy/basic_geometry.py
solid2_legacy/examples/legacy/basic_scad_include.py
solid2_legacy/examples/legacy/bom_scad.py
solid2_legacy/examples/legacy/convenience_example.py
solid2_legacy/examples/legacy/hole_example.py
solid2_legacy/examples/legacy/koch.py
solid2_legacy/examples/legacy/libs_example.py
solid2_legacy/examples/legacy/mazebox/__init__.py
solid2_legacy/examples/legacy/mazebox/inset.py
solid2_legacy/examples/legacy/mazebox/maze7.png
solid2_legacy/examples/legacy/mazebox/mazebox.py
solid2_legacy/examples/legacy/mazebox/trianglemath.py
solid2_legacy/examples/legacy/path_extrude_example.py
solid2_legacy/examples/legacy/run_all_examples.sh
solid2_legacy/examples/legacy/screw_thread_example.py
solid2_legacy/examples/legacy/sierpinski.py
solid2_legacy/examples/legacy/solidpython_template.py
solid2_legacy/examples/legacy/splines_example.py
solid2_legacy/examples/xx_legacy_bill_of_materials_example.py
solid2_legacy/examples/xx_legacy_compatibility.py
solid2_legacy/examples/xx_legacy_hole_example.py
solid2_legacy/extrude_along_path.py
solid2_legacy/part_hole.py
solid2_legacy/patch_euclid.py
solid2_legacy/repr_png.py
solid2_legacy/screw_thread.py
solid2_legacy/splines.py
solid2_legacy/types.py
solid2_legacy/utils.py
solidpython2_legacy-0.1.1.dist-info/METADATA
solidpython2_legacy-0.1.1.dist-info/WHEEL
solidpython2_legacy-0.1.1.dist-info/RECORD
