Metadata-Version: 2.1
Name: solidpython2-legacy
Version: 0.1.1
Summary: the legacy extension for SolidPython 2.x.x which provides some backwards compatibility to SolidPython 1.x.x
License: LGPL
Author: jeff
Author-email: 1105041+jeff-dh@users.noreply.github.com
Requires-Python: >=3.8,<4.0
Classifier: License :: Other/Proprietary License
Classifier: Programming Language :: Python :: 3
Classifier: Programming Language :: Python :: 3.8
Classifier: Programming Language :: Python :: 3.9
Classifier: Programming Language :: Python :: 3.10
Classifier: Programming Language :: Python :: 3.11
Requires-Dist: euclid3 (>=0.1.0,<0.2.0)
Requires-Dist: prettytable (==0.7.2)
Requires-Dist: pypng (>=0.0.19,<0.0.20)
Requires-Dist: solidpython2 (>=2.0.0-beta.1,<3.0.0)
